dockermatrix.py
dockermatrix-0.2.0.dist-info/DESCRIPTION.rst
dockermatrix-0.2.0.dist-info/METADATA
dockermatrix-0.2.0.dist-info/RECORD
dockermatrix-0.2.0.dist-info/WHEEL
dockermatrix-0.2.0.dist-info/metadata.json
dockermatrix-0.2.0.dist-info/top_level.txt
