Metadata-Version: 2.0
Name: dockermatrix
Version: 0.2.0
Summary: Build Dockerfiles from matrices automatically using templates
Home-page: https://github.com/webplates/dockermatrix
Author: Márk Sági-Kazár
Author-email: mark.sagikazar@gmail.com
License: MIT
Keywords: docker hub matrix dockerfile
Platform: UNKNOWN
Classifier: Development Status :: 3 - Alpha
Classifier: Intended Audience :: Developers
Classifier: Topic :: Software Development :: Build Tools
Classifier: License :: OSI Approved :: MIT License
Classifier: Programming Language :: Python :: 3.5
Requires-Dist: jinja2
Requires-Dist: requests
Requires-Dist: semver (>=2.7)
